asd_database/__init__.py
asd_database/core.py
asd_database-1.0.0.dist-info/METADATA
asd_database-1.0.0.dist-info/WHEEL
asd_database-1.0.0.dist-info/top_level.txt
asd_database-1.0.0.dist-info/RECORD
