Metadata-Version: 2.2
Name: asd-database
Version: 1.0.0
Summary: An simple database for your projects.
Home-page: 
Author: Il Tuo Nome
Author-email: simplerpy@gmail.com
Classifier: Programming Language :: Python :: 3
Classifier: License :: OSI Approved :: MIT License
Classifier: Operating System :: OS Independent
Requires-Python: >=3.6
Dynamic: author
Dynamic: author-email
Dynamic: classifier
Dynamic: description
Dynamic: description-content-type
Dynamic: requires-python
Dynamic: summary
